{
	"sheela_url": "https://ai.vsolgmi.com/api1/",
	"faq_url": "https://fhb.faqs.vsolgmi.com/",
	"google_map_url": "https://maps.googleapis.com/maps/api/place/autocomplete/json",
	"google_place_api_key": "AIzaSyBJVk-_P30Ix8eqfZj0E7nWJdWJDbz3e6I",
	"google_map_place_detail_url": "https://maps.googleapis.com/maps/api/place/details/json",
	"google_address_from_location_url": "https://maps.googleapis.com/maps/api/geocode/json",
	"google_static_map_url": "https://maps.googleapis.com/maps/api/staticmap?center=&",
	"myfhb_base_url": "https://w1mygk3kis4ksmnjdk.vsolgmi.com/api/",
	"myfhb_base_url_deviceReadings": "https://w1mygk3kis4ksmnjdk.vsolgmi.com/api/",
	"firebase_chat_notification_token" : "AAAA9UvO5fM:APA91bGaRuI7HrZmpIc0XUmEJ_toWEBOQMLGGm4MJ7E_bVSmNz6TDGb_aRCCgDw5ON1BtNbpds-VyoJKTTLJqY_u2xkmVpIIZv_jt_vRElbXSeWLB16w3oPr3xC8BgGuyNbpd1-R6Usr",
	"region_code": "IN",
	"power_bi_url":  "https://portal.qurplus.com/assets/powerbi-mobile.html",
	"qurhub_base_url": "https://w1mygk3kis4ksmnjdk.vsolgmi.com/qur-hub/",
	"true_desk_url": "https://trudesk.vsolgmi.com/api/v2/",
	"deactivate_account_url": "https://portal.qurplus.com/assets/qur_account_deactivation.html?type=myFHBMobile"
}
